tsl/__init__.py
tsl/app.py
tsl/tsl_pylib/__init__.py
tsl/tsl_pylib/io/__init__.py
tsl/tsl_pylib/io/load_csv.py
tsl/tsl_pylib/visualization/__init__.py
tsl/tsl_pylib/visualization/plot.py
timeseries_labeling-0.2.1.dist-info/LICENSE
timeseries_labeling-0.2.1.dist-info/METADATA
timeseries_labeling-0.2.1.dist-info/WHEEL
timeseries_labeling-0.2.1.dist-info/entry_points.txt
timeseries_labeling-0.2.1.dist-info/top_level.txt
timeseries_labeling-0.2.1.dist-info/RECORD
