Metadata-Version: 2.1
Name: timeseries-labeling
Version: 0.2.1
Summary: Simple annotation/labeling of events in timeseries
Home-page: https://github.com/matnil-star/timeseries_labeling
Author: Mattias Nilsson
Author-email: dan.mattias.nilsson@gmail.com
License: MIT
Platform: UNKNOWN
Requires-Python: >=3.7
Requires-Dist: numpy
Requires-Dist: pandas
Requires-Dist: dash
Requires-Dist: plotly
